trame/modules/__init__.py
trame/modules/image_tools.py
trame/widgets/__init__.py
trame/widgets/image_tools.py
trame_image_tools/__init__.py
trame_image_tools/widgets.py
trame_image_tools/module/__init__.py
trame_image_tools/module/serve/trame_image_tools.umd.js
trame_image_tools/module/serve/trame_image_tools.umd.js.map
trame_image_tools-1.0.2.dist-info/METADATA
trame_image_tools-1.0.2.dist-info/WHEEL
trame_image_tools-1.0.2.dist-info/top_level.txt
trame_image_tools-1.0.2.dist-info/RECORD
